mipath/__init__.py
mipath/analysis.py
mipath/decomposition.py
mipath/pathways.py
mipath/scoring.py
mipath/significance.py
mipathway-0.0.7.dist-info/LICENSE
mipathway-0.0.7.dist-info/METADATA
mipathway-0.0.7.dist-info/WHEEL
mipathway-0.0.7.dist-info/top_level.txt
mipathway-0.0.7.dist-info/RECORD
