Metadata-Version: 2.1
Name: mipathway
Version: 0.0.7
Summary: MIPath pathway analysis method
Author: Gustavo S. Jeuken
Author-email: gjeuken@gmail.com
License: Apache Software Licence 2
Classifier: Programming Language :: Python :: 3
Classifier: License :: OSI Approved :: Apache Software License
Classifier: Operating System :: OS Independent
Requires-Python: >=3.7
License-File: LICENSE
Requires-Dist: numpy
Requires-Dist: scipy
Requires-Dist: pandas
Requires-Dist: scikit-learn
Requires-Dist: igraph
Requires-Dist: leidenalg
Requires-Dist: joblib
Requires-Dist: requests
Requires-Dist: pynndescent <=0.5.8
